lineproto/__init__.py
lineproto/line.py
lineproto-0.2.1.dist-info/METADATA
lineproto-0.2.1.dist-info/WHEEL
lineproto-0.2.1.dist-info/top_level.txt
lineproto-0.2.1.dist-info/RECORD
